repchar/__init__.py
repchar/reporter.py
repchar/scripts/__init__.py
repchar/scripts/repchar_script.py
repchar-1.0.2.dist-info/METADATA
repchar-1.0.2.dist-info/RECORD
repchar-1.0.2.dist-info/WHEEL
repchar-1.0.2.dist-info/entry_points.txt
repchar-1.0.2.dist-info/top_level.txt
