Metadata-Version: 2.1
Name: repchar
Version: 1.0.2
Summary: Simple reporter for characters used in a file
Home-page: https://github.com/rotula/repchar
Author: Clemens Radl
Author-email: clemens.radl@googlemail.com
License: MIT
Keywords: unicode
Platform: UNKNOWN
Classifier: License :: OSI Approved :: MIT License
Classifier: Development Status :: 5 - Production/Stable
Classifier: Programming Language :: Python
Classifier: Programming Language :: Python :: 2.7
Classifier: Programming Language :: Python :: 3.6
Classifier: Environment :: Console
Classifier: Topic :: Text Processing
Classifier: Topic :: Text Processing :: General
